edawesome/__init__.py
edawesome/configs.py
edawesome/eda.py
edawesome/eda_help.py
edawesome/html/edawesome/configs.html
edawesome/html/edawesome/eda.html
edawesome/html/edawesome/eda_help.html
edawesome/html/edawesome/index.html
edawesome/html/edawesome/pd_apply.html
edawesome/html/edawesome/pd_help.html
edawesome/html/edawesome/sklearn_help.html
edawesome/html/edawesome/sns_help.html
edawesome/html/edawesome/str_help.html
edawesome/pd_apply.py
edawesome/pd_help.py
edawesome/sklearn_help.py
edawesome/sns_help.py
edawesome/str_help.py
edawesome-0.1.5.dist-info/WHEEL
edawesome-0.1.5.dist-info/METADATA
edawesome-0.1.5.dist-info/RECORD
