Metadata-Version: 2.1
Name: edawesome
Version: 0.1.5
Summary: Quick, easy and customizable data analysis with pandas and seaborn
Author: Timofei Ryko
Author-email: timofei.ryko@gmail.com
Requires-Python: >=3.8,<3.11
Classifier: Programming Language :: Python :: 3
Classifier: Programming Language :: Python :: 3.8
Classifier: Programming Language :: Python :: 3.9
Classifier: Programming Language :: Python :: 3.10
Requires-Dist: ipython (>=8.5.0,<9.0.0)
Requires-Dist: kaggle (>=1.5.12,<2.0.0)
Requires-Dist: pandas (>=1.5.2,<2.0.0)
Requires-Dist: patool (>=1.12,<2.0)
Requires-Dist: pyspark (>=3.3.1,<4.0.0)
Requires-Dist: scikit-learn (>=1.2.0)
Requires-Dist: scipy (>=1.8.0,<1.9.0)
Requires-Dist: seaborn (>=0.12.1,<0.13.0)
Requires-Dist: statsmodels (>=0.13.5,<0.14.0)
Requires-Dist: transitions (>=0.9.0,<0.10.0)
